gokart/__init__.py
gokart/build.py
gokart/config_params.py
gokart/file_processor.py
gokart/gcs_config.py
gokart/gcs_obj_metadata_client.py
gokart/gcs_zip_client.py
gokart/info.py
gokart/mypy.py
gokart/object_storage.py
gokart/pandas_type_config.py
gokart/parameter.py
gokart/py.typed
gokart/required_task_output.py
gokart/run.py
gokart/s3_config.py
gokart/s3_zip_client.py
gokart/target.py
gokart/task.py
gokart/task_complete_check.py
gokart/utils.py
gokart/worker.py
gokart/workspace_management.py
gokart/zip_client.py
gokart/zip_client_util.py
gokart/conflict_prevention_lock/task_lock.py
gokart/conflict_prevention_lock/task_lock_wrappers.py
gokart/errors/__init__.py
gokart/file_processor/__init__.py
gokart/file_processor/base.py
gokart/file_processor/pandas.py
gokart/file_processor/polars.py
gokart/in_memory/__init__.py
gokart/in_memory/data.py
gokart/in_memory/repository.py
gokart/in_memory/target.py
gokart/slack/__init__.py
gokart/slack/event_aggregator.py
gokart/slack/slack_api.py
gokart/slack/slack_config.py
gokart/testing/__init__.py
gokart/testing/check_if_run_with_empty_data_frame.py
gokart/testing/pandas_assert.py
gokart/tree/task_info.py
gokart/tree/task_info_formatter.py
gokart-1.10.3.dist-info/METADATA
gokart-1.10.3.dist-info/WHEEL
gokart-1.10.3.dist-info/licenses/LICENSE
gokart-1.10.3.dist-info/RECORD
