Metadata-Version: 2.4
Name: gokart
Version: 1.10.3
Summary: Gokart solves reproducibility, task dependencies, constraints of good code, and ease of use for Machine Learning Pipeline. [Documentation](https://gokart.readthedocs.io/en/latest/)
Project-URL: Homepage, https://github.com/m3dev/gokart
Project-URL: Repository, https://github.com/m3dev/gokart
Project-URL: Documentation, https://gokart.readthedocs.io/en/latest/
Author: M3, inc.
License-Expression: MIT
License-File: LICENSE
Classifier: Development Status :: 5 - Production/Stable
Classifier: License :: OSI Approved :: MIT License
Classifier: Programming Language :: Python :: 3
Classifier: Programming Language :: Python :: 3.10
Classifier: Programming Language :: Python :: 3.11
Classifier: Programming Language :: Python :: 3.12
Classifier: Programming Language :: Python :: 3.13
Requires-Python: <4,>=3.10
Requires-Dist: apscheduler
Requires-Dist: backoff
Requires-Dist: boto3
Requires-Dist: dill
Requires-Dist: google-api-python-client
Requires-Dist: google-auth
Requires-Dist: luigi
Requires-Dist: numpy
Requires-Dist: pandas
Requires-Dist: pyarrow
Requires-Dist: redis
Requires-Dist: slack-sdk
Requires-Dist: typing-extensions>=4.11.0; python_version < '3.13'
Requires-Dist: uritemplate
Provides-Extra: polars
Requires-Dist: polars>=0.19.0; extra == 'polars'
